BiasedErasure/__init__.py
BiasedErasure/delayed_erasure_decoders/Experimental_Loss_Decoder.py
BiasedErasure/delayed_erasure_decoders/HeraldedCircuit_FREE_LD.py
BiasedErasure/delayed_erasure_decoders/HeraldedCircuit_SWAP_LD.py
BiasedErasure/delayed_erasure_decoders/MLE_Loss_Decoder.py
BiasedErasure/delayed_erasure_decoders/__init__.py
BiasedErasure/main_code/LogicalCircuit.py
BiasedErasure/main_code/LogicalCircuitMBQC.py
BiasedErasure/main_code/Simulator.py
BiasedErasure/main_code/StabilizerCode.py
BiasedErasure/main_code/XZZX.py
BiasedErasure/main_code/__init__.py
BiasedErasure/main_code/circuits.py
BiasedErasure/main_code/noise_channels.py
BiasedErasure/main_code/simulate.py
BiasedErasure/main_code/utilities.py
BiasedErasure/main_code/xzzx_circuit.py
BiasedErasure/main_code/xzzx_circuit_noisy.py
BiasedErasure/main_code/xzzx_cluster.py
BiasedErasure/main_code/xzzx_cluster_noisy.py
BiasedErasure-0.1.6.dist-info/LICENSE
BiasedErasure-0.1.6.dist-info/METADATA
BiasedErasure-0.1.6.dist-info/WHEEL
BiasedErasure-0.1.6.dist-info/top_level.txt
BiasedErasure-0.1.6.dist-info/RECORD
