Metadata-Version: 2.1
Name: BiasedErasure
Version: 0.1.6
Summary: Simulate logical circuits with loss errors with efficient smart decoding
Author: Gefen Baranes and Pablo Bonilla
Author-email: gefenbaranes123@gmail.com
License: LICENSE
License-File: LICENSE
Requires-Dist: networkx (==2.8.4)
Requires-Dist: matplotlib (==3.5.2)
Requires-Dist: stim (==1.12.0)
Requires-Dist: pymatching (==2.1.0)
Requires-Dist: sinter (==1.11.0)
Requires-Dist: scipy (==1.9.1)
Requires-Dist: numpy (==1.21.6)
